pdf_add_outline/__init__.py
pdf_add_outline/main.py
pdf_add_outline-0.1.1.dist-info/LICENSE
pdf_add_outline-0.1.1.dist-info/WHEEL
pdf_add_outline-0.1.1.dist-info/entry_points.txt
pdf_add_outline-0.1.1.dist-info/METADATA
pdf_add_outline-0.1.1.dist-info/RECORD
