Metadata-Version: 2.1
Name: pdf-add-outline
Version: 0.1.1
Summary: Programmatically add an outline to a PDF.
Home-page: https://github.com/sameersismail/pdf-add-outline
License: MIT
Author: Sameer Ismail
Author-email: 38896593+sameersismail@users.noreply.github.com
Requires-Python: >=3.10,<4.0
Classifier: License :: OSI Approved :: MIT License
Classifier: Programming Language :: Python :: 3
Classifier: Programming Language :: Python :: 3.10
Classifier: Programming Language :: Python :: 3.11
Requires-Dist: pikepdf (==6.2.9)
Project-URL: Documentation, https://github.com/sameersismail/pdf-add-outline
Project-URL: Repository, https://github.com/sameersismail/pdf-add-outline
